[
  {
    "keyword": "퇴직금계산기",
    "autocomplete": ["퇴직금계산기 세후", "퇴직금 계산기준", "알바 퇴직금계산기", "퇴직금계산기 세금"],
    "selected_keywords": ["퇴직금계산기 세후", "퇴직금 계산기준"],
    "title": "퇴직금계산기 세후 실수령 계산기준",
    "char_count": 18
  },
  {
    "keyword": "부가세환급일",
    "autocomplete": ["2026 부가세 환급일", "개인사업자 부가세 환급일", "부가세 환급일 조회", "부가세 환급 일정"],
    "selected_keywords": ["2026 부가세 환급일", "개인사업자 부가세 환급일"],
    "title": "부가세환급일 2026 개인사업자 환급 일정",
    "char_count": 21
  },
  {
    "keyword": "시급계산기",
    "autocomplete": ["시급계산기 주휴수당", "2026년 최저시급 계산기", "시급계산기 세후", "알바 시급 계산기"],
    "selected_keywords": ["시급계산기 주휴수당", "2026년 최저시급 계산기"],
    "title": "시급계산기 주휴수당 포함 2026년 최저시급",
    "char_count": 21
  },
  {
    "keyword": "실급여계산기",
    "autocomplete": ["실급여 계산기"],
    "selected_keywords": ["실급여 계산기"],
    "title": "실급여계산기 월급 실수령 바로 계산",
    "char_count": 19
  },
  {
    "keyword": "연말정산간소화",
    "autocomplete": ["연말정산 간소화서비스", "홈택스 연말정산 간소화", "손택스 연말정산 간소화", "연말정산 간소화 기간"],
    "selected_keywords": ["연말정산 간소화서비스", "홈택스 연말정산 간소화"],
    "title": "연말정산간소화 홈택스 간소화서비스 이용",
    "char_count": 21
  },
  {
    "keyword": "4대보험계산기",
    "autocomplete": ["4대보험계산기 실수령", "2026년 4대보험 계산기", "급여 4대보험 계산기", "4대보험 계산 기준"],
    "selected_keywords": ["4대보험계산기 실수령", "2026년 4대보험 계산기"],
    "title": "4대보험계산기 실수령 2026년 급여 기준",
    "char_count": 20
  },
  {
    "keyword": "시간계산기",
    "autocomplete": ["근무시간 계산기", "알바 시간 계산기", "주휴시간 계산기", "날짜 시간 계산기"],
    "selected_keywords": ["근무시간 계산기", "주휴시간 계산기"],
    "title": "시간계산기 알바 근무시간 주휴시간 산출",
    "char_count": 20
  },
  {
    "keyword": "3.3%계산기",
    "autocomplete": ["세금 3.3% 계산기", "알바 세금 3.3% 계산기", "소득세 3.3% 계산기", "월급 3.3% 계산기"],
    "selected_keywords": ["알바 세금 3.3% 계산기", "소득세 3.3% 계산기"],
    "title": "3.3%계산기 알바 세금 소득세 공제",
    "char_count": 18
  },
  {
    "keyword": "부가세계산기",
    "autocomplete": ["부가세 계산기 1.1", "부가세 계산기 공식", "부가세 계산기 엑셀", "네이버 부가세 계산기"],
    "selected_keywords": ["부가세 계산기 1.1", "부가세 계산기 공식"],
    "title": "부가세계산기 1.1 나누기 공식 계산법",
    "char_count": 19
  },
  {
    "keyword": "공급가액계산기",
    "autocomplete": ["공급가액 계산기", "공급가액 계산기 방법", "공급가액 계산기 엑셀"],
    "selected_keywords": ["공급가액 계산기 방법", "공급가액 계산기 엑셀"],
    "title": "공급가액계산기 엑셀 계산 방법 공식",
    "char_count": 19
  },
  {
    "keyword": "사직서양식",
    "autocomplete": ["사직서 양식 다운로드", "사직서 양식 한글", "권고사직서 양식", "사직서 양식 무료"],
    "selected_keywords": ["사직서 양식 다운로드", "사직서 양식 한글"],
    "title": "사직서양식 한글 무료 다운로드",
    "char_count": 16
  },
  {
    "keyword": "연차계산기",
    "autocomplete": ["연차계산기 입사일", "고용노동부 연차계산기", "연차 계산 기준", "연차 계산기 앱"],
    "selected_keywords": ["연차계산기 입사일", "고용노동부 연차계산기"],
    "title": "연차계산기 입사일 기준 고용노동부 연차",
    "char_count": 21
  },
  {
    "keyword": "이지샵",
    "autocomplete": ["이지샵 카드단말기", "이지샵 장부", "이지샵 복식부기", "이지샵 후기"],
    "selected_keywords": ["이지샵 카드단말기", "이지샵 장부"],
    "title": "이지샵 카드단말기 연동 장부 관리",
    "char_count": 18
  },
  {
    "keyword": "월급세후계산기",
    "autocomplete": ["월급 세후 계산기"],
    "selected_keywords": ["월급 세후 계산기"],
    "title": "월급세후계산기 4대보험 공제 실수령액",
    "char_count": 20
  },
  {
    "keyword": "시말서양식",
    "autocomplete": ["시말서 양식 예시", "시말서 양식 쓰는법", "시말서 양식 무료 다운", "시말서 양식 다운"],
    "selected_keywords": ["시말서 양식 예시", "시말서 양식 쓰는법"],
    "title": "시말서양식 쓰는법 예시 무료 다운",
    "char_count": 18
  },
  {
    "keyword": "경리나라",
    "autocomplete": ["경리나라 프로그램", "경리나라 급여", "경리나라 가격", "경리나라 무료"],
    "selected_keywords": ["경리나라 프로그램", "경리나라 급여"],
    "title": "경리나라 프로그램 급여 관리 가격",
    "char_count": 18
  },
  {
    "keyword": "세후계산기",
    "autocomplete": ["연봉 세후 계산기", "세전 세후 계산기", "퇴직금 세후 계산기", "2026 세후 계산기"],
    "selected_keywords": ["연봉 세후 계산기", "세전 세후 계산기"],
    "title": "세후계산기 연봉 세전 세후 실수령 비교",
    "char_count": 21
  },
  {
    "keyword": "소상공인정책자금",
    "autocomplete": ["소상공인 정책자금 대출", "소상공인 정책자금 신청", "소상공인 정책자금 2026", "소상공인 정책자금 직접대출"],
    "selected_keywords": ["소상공인 정책자금 대출", "소상공인 정책자금 신청"],
    "title": "소상공인정책자금 2026 대출 신청 자격",
    "char_count": 21
  },
  {
    "keyword": "증여세면제한도",
    "autocomplete": ["자녀 증여세 면제한도", "부부 증여세 면제한도", "증여세 면제한도 1억", "부모 증여세 면제한도"],
    "selected_keywords": ["자녀 증여세 면제한도", "증여세 면제한도 1억"],
    "title": "증여세면제한도 자녀 1억 부모 증여",
    "char_count": 19
  },
  {
    "keyword": "소득세율표",
    "autocomplete": ["근로소득세율표", "2026년 소득세율표", "소득세율표 구간", "소득세율표 누진공제"],
    "selected_keywords": ["근로소득세율표", "소득세율표 구간"],
    "title": "소득세율표 2026년 근로소득세율 구간",
    "char_count": 20
  }
]